stk/__init__.py
stk/_version.py
stk/cage.py
stk/cof.py
stk/host_guest.py
stk/macrocycle.py
stk/metal_complex.py
stk/polymer.py
stk/py.typed
stk/rotaxane.py
stk/small.py
stk/_internal/__init__.py
stk/_internal/atom.py
stk/_internal/atom_info.py
stk/_internal/bond.py
stk/_internal/bond_info.py
stk/_internal/building_block.py
stk/_internal/constructed_molecule.py
stk/_internal/elements.py
stk/_internal/molecule.py
stk/_internal/periodic_info.py
stk/_internal/construction_result/__init__.py
stk/_internal/construction_result/construction_result.py
stk/_internal/construction_result/periodic.py
stk/_internal/construction_state/__init__.py
stk/_internal/construction_state/construction_state.py
stk/_internal/construction_state/graph_state.py
stk/_internal/construction_state/molecule_state/__init__.py
stk/_internal/construction_state/molecule_state/deletions_summary.py
stk/_internal/construction_state/molecule_state/molecule_state.py
stk/_internal/construction_state/molecule_state/placements_summary/__init__.py
stk/_internal/construction_state/molecule_state/placements_summary/atom_batch.py
stk/_internal/construction_state/molecule_state/placements_summary/bond_batch.py
stk/_internal/construction_state/molecule_state/placements_summary/placements_summary.py
stk/_internal/construction_state/molecule_state/reactions_summary/__init__.py
stk/_internal/construction_state/molecule_state/reactions_summary/atom_batch.py
stk/_internal/construction_state/molecule_state/reactions_summary/bond_batch.py
stk/_internal/construction_state/molecule_state/reactions_summary/reactions_summary.py
stk/_internal/databases/__init__.py
stk/_internal/databases/constructed_molecule.py
stk/_internal/databases/molecule.py
stk/_internal/databases/value.py
stk/_internal/databases/mongo_db/__init__.py
stk/_internal/databases/mongo_db/constructed_molecule.py
stk/_internal/databases/mongo_db/molecule.py
stk/_internal/databases/mongo_db/utilities.py
stk/_internal/databases/mongo_db/value.py
stk-2026.1.4.0.dist-info/licenses/LICENSE
stk-2026.1.4.0.dist-info/METADATA
stk-2026.1.4.0.dist-info/WHEEL
stk-2026.1.4.0.dist-info/entry_points.txt
stk-2026.1.4.0.dist-info/top_level.txt
stk-2026.1.4.0.dist-info/RECORD
