Metadata-Version: 2.4
Name: stk
Version: 2026.1.4.0
Maintainer-email: Lukas Turcani <lukasturcani93@gmail.com>, Andrew Tarzia <andrew.tarzia@gmail.com>
Project-URL: github, https://github.com/lukasturcani/stk
Project-URL: documentation, https://stk.readthedocs.io
Requires-Python: >=3.11
License-File: LICENSE
Requires-Dist: atomlite
Requires-Dist: scipy
Requires-Dist: matplotlib
Requires-Dist: pandas
Requires-Dist: pathos
Requires-Dist: seaborn
Requires-Dist: numpy
Requires-Dist: pymongo[srv]
Requires-Dist: MCHammer
Requires-Dist: SpinDry
Requires-Dist: vabene
Requires-Dist: rdkit!=2024.3.5
Provides-Extra: dev
Requires-Dist: ruff; extra == "dev"
Requires-Dist: moldoc==3.0.0; extra == "dev"
Requires-Dist: mypy; extra == "dev"
Requires-Dist: pip-tools; extra == "dev"
Requires-Dist: pytest<8; extra == "dev"
Requires-Dist: pytest-benchmark; extra == "dev"
Requires-Dist: pytest-datadir; extra == "dev"
Requires-Dist: pytest-lazy-fixture; extra == "dev"
Requires-Dist: pytest-cov; extra == "dev"
Requires-Dist: sphinx; extra == "dev"
Requires-Dist: sphinx-copybutton; extra == "dev"
Requires-Dist: sphinx-rtd-theme; extra == "dev"
Requires-Dist: twine; extra == "dev"
Requires-Dist: chemiscope; extra == "dev"
Dynamic: license-file
